[
  {
    "id": "366d39c1-7551-4cba-a37c-1df8ecfc36a9",
    "createdAt": "2026-05-05T17:54:10.801Z",
    "firstName": "Test",
    "lastName": "User",
    "email": "test.user@example.com",
    "phone": "+91 98765 43210",
    "college": "KLS GIT Belgavi",
    "year": "3rd Year",
    "category": "General Pass (All Events)",
    "team": "Solo",
    "notes": "Local test registration"
  },
  {
    "id": "a6f4b10c-9e9d-4096-b7ed-6e38eac994dc",
    "createdAt": "2026-05-05T17:54:33.767Z",
    "firstName": "VANSHREE",
    "lastName": "GAVADE",
    "email": "dalvivanu2006@gmail.com",
    "phone": "7499979083",
    "college": "kls git",
    "year": "1st Year",
    "category": "Technical — Hackathon",
    "team": "TechWave",
    "notes": "nothing"
  },
  {
    "id": "d56b6674-dce3-4dd9-b1d9-6a3fade1d75a",
    "createdAt": "2026-05-05T17:55:07.479Z",
    "firstName": "Chinmay",
    "lastName": "Gavade",
    "email": "chinmay.p.g001@gmail.com",
    "phone": "9036994874",
    "college": "kls git",
    "year": "1st Year",
    "category": "Technical — Hackathon",
    "team": "TechWave",
    "notes": ""
  },
  {
    "id": "13733fc3-0b0e-4451-878b-24e3a5d83da5",
    "createdAt": "2026-05-05T18:11:15.364Z",
    "firstName": "Test",
    "lastName": "User",
    "email": "test@example.com",
    "phone": "+91 9876543210",
    "college": "Test College",
    "year": "2nd Year",
    "category": "Technical — Hackathon",
    "team": "",
    "notes": ""
  },
  {
    "id": "48dfdfb1-f387-48f2-a249-d293f81406e7",
    "createdAt": "2026-05-05T18:11:53.206Z",
    "firstName": "Chinmay",
    "lastName": "Gavade",
    "email": "chinmay.p.g001@gmail.com",
    "phone": "9036994874",
    "college": "kls git",
    "year": "1st Year",
    "category": "Technical — Hackathon",
    "team": "TechWave",
    "notes": ""
  },
  {
    "id": "b252523c-26fc-4bd3-be91-53b2b2c5bd96",
    "createdAt": "2026-05-05T18:19:58.405Z",
    "firstName": "Priya",
    "lastName": "Singh",
    "email": "priya.singh@college.edu",
    "phone": "+91 9876543210",
    "college": "KLS GIT",
    "year": "3rd Year",
    "category": "Cultural — Dance",
    "team": "",
    "notes": ""
  },
  {
    "id": "79bd54cc-87eb-45fd-86e5-fd1ee5968e6e",
    "createdAt": "2026-05-05T18:21:20.321Z",
    "firstName": "Chinmay",
    "lastName": "Gavade",
    "email": "chinmay.p.g001@gmail.com",
    "phone": "9036994874",
    "college": "kls git",
    "year": "1st Year",
    "category": "Technical — Hackathon",
    "team": "TechWave",
    "notes": ""
  },
  {
    "id": "3828ae8a-5b84-467f-a529-69824166d9a1",
    "createdAt": "2026-05-05T18:26:30.068Z",
    "firstName": "Chinmay",
    "lastName": "Gavade",
    "email": "chinmay.p.g001@gmail.com",
    "phone": "9036994874",
    "college": "kls git",
    "year": "1st Year",
    "category": "Technical — Hackathon",
    "team": "TechWave",
    "notes": ""
  },
  {
    "id": "90575ea8-688e-47c8-b5fd-c9e38dad6e52",
    "createdAt": "2026-05-05T18:33:17.903Z",
    "firstName": "Chinmay",
    "lastName": "Gavade",
    "email": "chinmay.p.g001@gmail.com",
    "phone": "9036994874",
    "college": "kls git",
    "year": "1st Year",
    "category": "Technical — Hackathon",
    "team": "TechWave",
    "notes": ""
  },
  {
    "id": "6c72862b-d37f-46a6-b0e3-cb9f04e334a4",
    "createdAt": "2026-05-05T18:38:57.937Z",
    "firstName": "aditya",
    "lastName": "Naik",
    "email": "adityanaik1608@gmail.com",
    "phone": "8951104795",
    "college": "kls git",
    "year": "1st Year",
    "category": "General Pass (All Events)",
    "team": "TechWave",
    "notes": ""
  }
]